bicsdifftest/__init__.py
bicsdifftest/cli.py
bicsdifftest/config/__init__.py
bicsdifftest/config/config_manager.py
bicsdifftest/config/environment.py
bicsdifftest/config/test_profiles.py
bicsdifftest/examples/fc_layer/Makefile
bicsdifftest/examples/fc_layer/README.md
bicsdifftest/examples/fc_layer/SUMMARY.md
bicsdifftest/examples/fc_layer/analyze_fixed_point.py
bicsdifftest/examples/fc_layer/analyze_weights.py
bicsdifftest/examples/fc_layer/debug_corner3.py
bicsdifftest/examples/fc_layer/debug_golden_model.py
bicsdifftest/examples/fc_layer/debug_hardware_direct.py
bicsdifftest/examples/fc_layer/debug_hardware_vs_golden.py
bicsdifftest/examples/fc_layer/debug_precision.py
bicsdifftest/examples/fc_layer/debug_verilog_corner3.py
bicsdifftest/examples/fc_layer/results.xml
bicsdifftest/examples/fc_layer/test_golden_model_mac.py
bicsdifftest/examples/fc_layer/config/fc_layer_test.yaml
bicsdifftest/examples/fc_layer/logs/difftest.log
bicsdifftest/examples/fc_layer/rtl/fc_layer.sv
bicsdifftest/examples/fc_layer/scripts/generate_test_data.py
bicsdifftest/examples/fc_layer/scripts/verify_integration.py
bicsdifftest/examples/fc_layer/sim_build/Vtop
bicsdifftest/examples/fc_layer/sim_build/Vtop.cpp
bicsdifftest/examples/fc_layer/sim_build/Vtop.h
bicsdifftest/examples/fc_layer/sim_build/Vtop.mk
bicsdifftest/examples/fc_layer/sim_build/Vtop__ALL.a
bicsdifftest/examples/fc_layer/sim_build/Vtop__ALL.cpp
bicsdifftest/examples/fc_layer/sim_build/Vtop__ALL.d
bicsdifftest/examples/fc_layer/sim_build/Vtop__ALL.o
bicsdifftest/examples/fc_layer/sim_build/Vtop__ConstPool_0.cpp
bicsdifftest/examples/fc_layer/sim_build/Vtop__Dpi.cpp
bicsdifftest/examples/fc_layer/sim_build/Vtop__Dpi.h
bicsdifftest/examples/fc_layer/sim_build/Vtop__Syms.cpp
bicsdifftest/examples/fc_layer/sim_build/Vtop__Syms.h
bicsdifftest/examples/fc_layer/sim_build/Vtop__TraceDecls__0__Slow.cpp
bicsdifftest/examples/fc_layer/sim_build/Vtop__Trace__0.cpp
bicsdifftest/examples/fc_layer/sim_build/Vtop__Trace__0__Slow.cpp
bicsdifftest-1.0.1.dist-info/METADATA
bicsdifftest-1.0.1.dist-info/WHEEL
bicsdifftest-1.0.1.dist-info/entry_points.txt
bicsdifftest-1.0.1.dist-info/top_level.txt
bicsdifftest-1.0.1.dist-info/RECORD
