Metadata-Version: 2.4
Name: BICSdifftest
Version: 1.0.1
Summary: Differential Testing Framework for Verilog Hardware Verification
Author-email: Guolin Yang <curryfromuestc@gmail.com>
Maintainer-email: Guolin Yang <curryfromuestc@gmail.com>
License: MIT
Project-URL: Homepage, https://github.com/curryfromuestc/BICSdifftest
Project-URL: Documentation, https://bicsdifftest.readthedocs.io/
Project-URL: Repository, https://github.com/curryfromuestc/BICSdifftest.git
Project-URL: Bug Reports, https://github.com/curryfromuestc/BICSdifftest/issues
Project-URL: Changelog, https://github.com/curryfromuestc/BICSdifftest/blob/main/CHANGELOG.md
Keywords: hardware verification,differential testing,verilog,cocotb,verilator,pytorch,golden model,rtl verification,hardware testing,eda
Classifier: Development Status :: 4 - Beta
Classifier: Intended Audience :: Developers
Classifier: Intended Audience :: Education
Classifier: Intended Audience :: Science/Research
Classifier: Topic :: Scientific/Engineering :: Electronic Design Automation (EDA)
Classifier: Topic :: Software Development :: Testing
Classifier: License :: OSI Approved :: MIT License
Classifier: Programming Language :: Python :: 3
Classifier: Programming Language :: Python :: 3.8
Classifier: Programming Language :: Python :: 3.9
Classifier: Programming Language :: Python :: 3.10
Classifier: Programming Language :: Python :: 3.11
Classifier: Programming Language :: Python :: 3.12
Classifier: Operating System :: OS Independent
Requires-Python: >=3.8
Requires-Dist: torch>=1.10.0
Requires-Dist: numpy>=1.20.0
Requires-Dist: PyYAML>=5.4.0
Requires-Dist: cocotb>=1.6.0
Requires-Dist: cocotb-test>=0.2.0
Requires-Dist: click>=8.0.0
Requires-Dist: jinja2>=3.0.0
Provides-Extra: dev
Requires-Dist: pytest>=6.0.0; extra == "dev"
Requires-Dist: pytest-cov>=2.10.0; extra == "dev"
Requires-Dist: flake8>=3.8.0; extra == "dev"
Requires-Dist: black>=21.0.0; extra == "dev"
Requires-Dist: pre-commit>=2.10.0; extra == "dev"
Requires-Dist: mypy>=0.910; extra == "dev"
Requires-Dist: isort>=5.9.0; extra == "dev"
Provides-Extra: docs
Requires-Dist: sphinx>=4.0.0; extra == "docs"
Requires-Dist: sphinx-rtd-theme>=1.0.0; extra == "docs"
Requires-Dist: myst-parser>=0.15.0; extra == "docs"
Provides-Extra: reporting
Requires-Dist: jinja2>=3.0.0; extra == "reporting"
Requires-Dist: matplotlib>=3.3.0; extra == "reporting"
Requires-Dist: plotly>=4.14.0; extra == "reporting"
Requires-Dist: pandas>=1.3.0; extra == "reporting"
Provides-Extra: all
Requires-Dist: BICSdifftest[dev,docs,reporting]; extra == "all"
